ram.v
module coincident_ram_1k8 (
    input wire clk,
    input wire we,             // Write Enable
    input wire [9:0] addr,     // 10-bit address = 5 row + 5 col(co-incident decoding)
    input wire [7:0] din,      // 8-bit data input
    output reg [7:0] dout      // 8-bit data output(useful in case of read)
);

    // Split address -- to make less use of nand gates in hardware
    wire [4:0] row_addr = addr[9:5];    // Top 5 bits for row
    wire [4:0] col_addr = addr[4:0];    // Bottom 5 bits for col

    // Memory: 32 rows × 32 cols of 8-bit values instead of the mem[0:1023]
    reg [7:0] mem [0:31][0:31];

    // Coincident decoding: Write and Read
    always @(posedge clk) begin
        if (we)
            mem[row_addr][col_addr] <= din; // Write to [row][col]
       
        dout <= mem[row_addr][col_addr];  // Read from [row][col]
    end

endmodule

ram_tb.v
`include "ram.v"  
`timescale 1ns/1ns
module tb_coincident_ram_1k8;
    reg clk;
    reg we;
    reg [9:0] addr;
    reg [7:0] din;
    wire [7:0] dout;

    // Module instantiation
    coincident_ram_1k8 DUT (
        .clk(clk),
        .we(we),
        .addr(addr),
        .din(din),
        .dout(dout)
    );

    // Clock generation: 10ns period
    always #5 clk = ~clk;

    initial begin
        $dumpfile("coincident_ram.vcd");
        $dumpvars(0, tb_coincident_ram_1k8);
        $monitor($time, " clk=%b we=%b addr=%h din=%h dout=%h", clk, we, addr, din, dout);

       
        clk = 0;
        we  = 0;
        addr = 10'd0;
        din = 8'd0;

        #2  we = 1; 
        addr = 10'd21; 
        din = 8'hAA;
        #10 we = 0;

        // Read back from address 21
        #10 addr = 10'd21;

        
        #10 we = 1; addr = 10'd228; din = 8'h5C;
        #10 we = 0;

        // Read back from address 228
        #10 addr = 10'd228;

       
        #10 addr = 10'd1023;

        #10 $finish;
    end
endmodule

coincident_ram.vcd
$date
	Sun Jul 27 01:28:30 2025
$end
$version
	Icarus Verilog
$end
$timescale
	1ns
$end
$scope module tb_coincident_ram_1k8 $end
$var wire 8 ! dout [7:0] $end
$var reg 10 " addr [9:0] $end
$var reg 1 # clk $end
$var reg 8 $ din [7:0] $end
$var reg 1 % we $end
$scope module DUT $end
$var wire 10 & addr [9:0] $end
$var wire 1 # clk $end
$var wire 8 ' din [7:0] $end
$var wire 1 % we $end
$var wire 5 ( row_addr [4:0] $end
$var wire 5 ) col_addr [4:0] $end
$var reg 8 * dout [7:0] $end
$upscope $end
$upscope $end
$enddefinitions $end
$comment Show the parameter values. $end
$dumpall
$end
#0
$dumpvars
bx *
b0 )
b0 (
b0 '
b0 &
0%
b0 $
0#
b0 "
bx !
$end
#2
b10101 )
b10101010 $
b10101010 '
b10101 "
b10101 &
1%
#5
1#
#10
0#
#12
0%
#15
b10101010 !
b10101010 *
1#
#20
0#
#25
1#
#30
0#
#32
b111 (
b100 )
b1011100 $
b1011100 '
b11100100 "
b11100100 &
1%
#35
bx !
bx *
1#
#40
0#
#42
0%
#45
b1011100 !
b1011100 *
1#
#50
0#
#55
1#
#60
0#
#62
b11111 (
b11111 )
b1111111111 "
b1111111111 &
#65
bx !
bx *
1#
